{
  "full_name": "سلمى عبدالرحمن وليد عثمان",
  "address": "25 ميدان السلام، سيدي جابر، الإسكندرية",
  "national_id": "28110282809186",
  "national_id_eastern": "٢٨١١٠٢٨٢٨٠٩١٨٦",
  "governorate_code": "28",
  "governorate_name": "أسوان",
  "is_male": false,
  "birth_year": 1981,
  "birth_month": 10,
  "birth_day": 28,
  "sample_id": "sample_0023",
  "severity": "heavy",
  "card_corners_in_degraded_image": [
    [
      795.8294677734375,
      242.32525634765625
    ],
    [
      1172.9566650390625,
      127.55926513671875
    ],
    [
      1362.7652587890625,
      998.3986206054688
    ],
    [
      461.0671081542969,
      960.5653076171875
    ]
  ]
}