{
  "full_name": "رامي عبدالله طارق أحمد",
  "address": "132 ميدان مكرم عبيد، ميت غمر، الدقهلية",
  "national_id": "30410050407538",
  "national_id_eastern": "٣٠٤١٠٠٥٠٤٠٧٥٣٨",
  "governorate_code": "04",
  "governorate_name": "السويس",
  "is_male": true,
  "birth_year": 2004,
  "birth_month": 10,
  "birth_day": 5,
  "field_bboxes": {
    "full_name": [
      526,
      192,
      751,
      229
    ],
    "address": [
      367,
      277,
      751,
      304
    ],
    "national_id": [
      546,
      364,
      751,
      385
    ]
  },
  "sample_id": "sample_0130",
  "severity": "medium",
  "card_corners_in_degraded_image": [
    [
      333.0090026855469,
      403.2491760253906
    ],
    [
      1213.7459716796875,
      168.6795654296875
    ],
    [
      1392.6591796875,
      814.4532470703125
    ],
    [
      499.133544921875,
      966.7452392578125
    ]
  ]
}